ppinit/__init__.py
ppinit/__main__.py
ppinit/assets/gitignore_content.txt
ppinit/assets/main_file_content.txt
ppinit/assets/licenses/AGPL-3.0.txt
ppinit/assets/licenses/Apache-2.0.txt
ppinit/assets/licenses/GPL-3.0.txt
ppinit/assets/licenses/MIT.txt
ppinit-0.3.0.dist-info/licenses/LICENSE
ppinit-0.3.0.dist-info/METADATA
ppinit-0.3.0.dist-info/WHEEL
ppinit-0.3.0.dist-info/entry_points.txt
ppinit-0.3.0.dist-info/top_level.txt
ppinit-0.3.0.dist-info/RECORD
