Metadata-Version: 2.4
Name: ppinit
Version: 0.3.0
Summary: A Python project initializer.
Author-email: Ritesh Karmakar <riteshkarmakar7407@gmail.com>
License-Expression: GPL-3.0
Project-URL: Homepage, https://github.com/riteshkarmakar/ppinit
Classifier: Programming Language :: Python :: 3
Classifier: Operating System :: OS Independent
Requires-Python: >=3.10
License-File: LICENSE
Dynamic: license-file
